MANIFEST.in
README
setup.py
auxygen/__init__.py
auxygen/executables.py
auxygen/utils.py
auxygen.egg-info/PKG-INFO
auxygen.egg-info/SOURCES.txt
auxygen.egg-info/dependency_links.txt
auxygen.egg-info/entry_points.txt
auxygen.egg-info/requires.txt
auxygen.egg-info/top_level.txt
auxygen/devices/__init__.py
auxygen/devices/blower.py
auxygen/devices/cryostream.py
auxygen/devices/iseg.py
auxygen/devices/lakeshore.py
auxygen/devices/logger.py
auxygen/gui/__init__.py
auxygen/gui/wblower.py
auxygen/gui/wcryo.py
auxygen/gui/wiseg.py
auxygen/gui/wlakeshore.py
auxygen/gui/wlogging.py
auxygen/gui/wscripted.py
auxygen/gui/wseq.py
auxygen/gui/ui/__init__.py
auxygen/gui/ui/resources_rc.py
auxygen/gui/ui/ui_lakeshore_sensors.py
auxygen/gui/ui/ui_lakeshore_widget.py
auxygen/gui/ui/ui_wblower.py
auxygen/gui/ui/ui_wcryo.py
auxygen/gui/ui/ui_wiseg.py
auxygen/gui/ui/ui_wlakeshore.py
auxygen/gui/ui/ui_wlogging.py
auxygen/gui/ui/ui_wscripted.py
auxygen/gui/ui/ui_wseq.py
auxygen/scripo/__init__.py
auxygen/scripo/blower.py
auxygen/scripo/cryostream.py
auxygen/scripo/iseg.py
auxygen/scripo/lakeshore.py
auxygen/scripo/motor.py
auxygen/scripo/utils.py