Metadata-Version: 1.1
Name: auxygen
Version: 2018.10.24.1
Summary: Drivers and scripting for Pylatus auxiliary equipment
Home-page: https://hg.3lp.cx/auxygen
Author: Vadim Dyadkin
Author-email: diadkin@esrf.fr
License: GPL
Platform: UNKNOWN
Classifier: License :: OSI Approved :: GNU General Public License v3 (GPLv3)
Classifier: Programming Language :: Python
Classifier: Programming Language :: Python :: 3.6
Classifier: Programming Language :: Python :: Implementation :: CPython
